qrem/__init__.py
qrem/backends_support/aws_braket/functions_aws_rigetti.py
qrem/backends_support/pyquil/QDT_pyquill.py
qrem/backends_support/pyquil/pyquil_utilities.py
qrem/backends_support/qiskit/QDT_qiskit.py
qrem/backends_support/qiskit/qiskit_utilities.py
qrem/benchmarks/__init__.py
qrem/benchmarks/benchmarks_functions.py
qrem/benchmarks/hamiltonians.py
qrem/characterization/__init__.py
qrem/characterization/characterization.py
qrem/characterization/characterization_routine.py
qrem/characterization/clustering_algorithms.py
qrem/characterization/neighbors_algorithms.py
qrem/cn/__init__.py
qrem/cn/mitigation.py
qrem/cn/simulation.py
qrem/cn/mitigtools/__init__.py
qrem/cn/modeltools/__init__.py
qrem/cn/simtools/__init__.py
qrem/cn/simtools/auxiliary_merging_functions.py
qrem/cn/simtools/custom_model_creator.py
qrem/cn/simtools/noisy_simulationsKKM.py
qrem/common/__init__.py
qrem/common/config.py
qrem/common/constants.py
qrem/common/convert.py
qrem/common/io.py
qrem/common/math.py
qrem/common/povmtools.py
qrem/common/printer.py
qrem/common/probability.py
qrem/common/registers.py
qrem/common/scipy_optimizers_wrappers.py
qrem/common/utils.py
qrem/common/experiment/__init__.py
qrem/common/experiment/information_completeness.py
qrem/common/experiment/tomography.py
qrem/common/experiment/tomoutils/__init__.py
qrem/common/experiment/tomoutils/algortithmic_circuits.py
qrem/common/external/__init__.py
qrem/common/external/hyperplane_projections.py
qrem/common/external/CBB/__init__.py
qrem/common/external/CBB/branchandbound_tools.py
qrem/common/external/CBB/spin_models.py
qrem/common/external/ncpol2sdpa/__init__.py
qrem/common/external/ncpol2sdpa/chordal_extension.py
qrem/common/external/ncpol2sdpa/cvxpy_utils.py
qrem/common/external/ncpol2sdpa/faacets_relaxation.py
qrem/common/external/ncpol2sdpa/moroder_hierarchy.py
qrem/common/external/ncpol2sdpa/mosek_utils.py
qrem/common/external/ncpol2sdpa/nc_utils.py
qrem/common/external/ncpol2sdpa/physics_utils.py
qrem-0.2.0.dist-info/LICENSE
qrem-0.2.0.dist-info/METADATA
qrem-0.2.0.dist-info/WHEEL
qrem-0.2.0.dist-info/top_level.txt
qrem-0.2.0.dist-info/RECORD
