Metadata-Version: 2.1
Name: qrem
Version: 0.2.0
Summary: QREM package provides a versatile set of tools for the characterization and mitigation of readout noise in NISQ quantum devices.
Author-email: "Jan Tuziemski, Filip Maciejewski, Joanna Majsak, Oskar Słowik, Marcin Kotowski, Katarzyna Kowalczyk-Murynka, Paweł Przewłocki, Piotr Podziemski, Michał Oszmaniec" <oszmaniec@cft.edu.pl>
Maintainer-email: Michał Oszmaniec <oszmaniec@cft.edu.pl>
Project-URL: Homepage, https://github.com/cft-nisq/qrem
Project-URL: GitHub, https://github.com/cft-nisq/qrem
Project-URL: Documentation, https://cft-nisq.github.io/qrem/index.html
Project-URL: Article, http://arxiv.org/abs/2311.10661
Keywords: quantum,nisq,quantum-devices,quantum-physics,physics,sdk,qiskit
Classifier: Development Status :: 3 - Alpha
Classifier: Environment :: Console
Classifier: Operating System :: Microsoft :: Windows
Classifier: Operating System :: MacOS
Classifier: Operating System :: POSIX :: Linux
Classifier: License :: OSI Approved :: Apache Software License
Classifier: Operating System :: OS Independent
Classifier: Intended Audience :: Developers
Classifier: Intended Audience :: Science/Research
Classifier: Topic :: Scientific/Engineering :: Physics
Classifier: Programming Language :: Python :: 3.7
Classifier: Programming Language :: Python :: 3.8
Classifier: Programming Language :: Python :: 3.9
Classifier: Programming Language :: Python :: 3.10
Requires-Python: >=3.8
License-File: LICENSE
Requires-Dist: ipykernel >=6.1.0
Requires-Dist: python-dotenv >=1.0.0
Requires-Dist: colorama >=0.4.6
Requires-Dist: orjson >=3.9.10
Requires-Dist: tqdm >=4.64.0
Requires-Dist: numpy <1.24,>=1.18.0
Requires-Dist: scipy >=1.7.0
Requires-Dist: pandas >=1.5.0
Requires-Dist: picos >=2.4.0
Requires-Dist: qiskit >=0.43.3
Requires-Dist: qiskit-ibm-runtime >=0.11.2
Requires-Dist: qiskit-ibm-provider >=0.6.1
Requires-Dist: qiskit-braket-provider >=0.0.3
Requires-Dist: amazon-braket-sdk >=1.61.0
Requires-Dist: qutip >=4.7.1
Requires-Dist: matplotlib >=3.6.0
Requires-Dist: seaborn >=0.12.0
Requires-Dist: networkx <3.0,>=0.12.0
Requires-Dist: sympy >=1.11.0
Requires-Dist: pyquil >=4.0.3
Requires-Dist: configargparse >=1.5.0
Requires-Dist: pysat >=3.1.0
Provides-Extra: test
Requires-Dist: pytest-cov ~=3.0.0 ; extra == 'test'
Provides-Extra: visualization
Requires-Dist: manim >=0.17.2 ; extra == 'visualization'
